nonebot_plugin_today_waifu/__init__.py
nonebot_plugin_today_waifu/config.py
nonebot_plugin_today_waifu/record.py
nonebot_plugin_today_waifu/utils.py
nonebot_plugin_today_waifu-0.1.10.dist-info/LICENSE
nonebot_plugin_today_waifu-0.1.10.dist-info/METADATA
nonebot_plugin_today_waifu-0.1.10.dist-info/WHEEL
nonebot_plugin_today_waifu-0.1.10.dist-info/RECORD
