Metadata-Version: 2.3
Name: nonebot-plugin-today-waifu
Version: 0.1.10
Summary: Nonebot2插件 可以随机抽取群友作为老婆
License: MIT
Author: glamorgan9826
Author-email: glamorgan9826@gmail.com
Requires-Python: >=3.9,<4.0
Classifier: License :: OSI Approved :: MIT License
Classifier: Programming Language :: Python :: 3
Classifier: Programming Language :: Python :: 3.9
Classifier: Programming Language :: Python :: 3.10
Classifier: Programming Language :: Python :: 3.11
Classifier: Programming Language :: Python :: 3.12
Classifier: Programming Language :: Python :: 3.13
Requires-Dist: httpx (>=0.28.1,<0.29.0)
Requires-Dist: nonebot-adapter-onebot (>=2.4.6,<3.0.0)
Requires-Dist: nonebot-plugin-alconna (>=0.57.6,<0.58.0)
Requires-Dist: nonebot-plugin-uninfo (>=0.7.3,<0.8.0)
Requires-Dist: nonebot2[fastapi] (>=2.4.2,<3.0.0)
